MohamedSataryNinthTest/__init__.py
MohamedSataryNinthTest/bye.py
MohamedSataryNinthTest/helloWorld.py
MohamedSataryNinthTest/anothaone/__init__.py
MohamedSataryNinthTest/anothaone/goodBye.py
MohamedSataryNinthTest-0.0.1.dist-info/METADATA
MohamedSataryNinthTest-0.0.1.dist-info/WHEEL
MohamedSataryNinthTest-0.0.1.dist-info/top_level.txt
MohamedSataryNinthTest-0.0.1.dist-info/RECORD
